odoo/addons/queue_job_subscribe/README.rst
odoo/addons/queue_job_subscribe/__init__.py
odoo/addons/queue_job_subscribe/__manifest__.py
odoo/addons/queue_job_subscribe/i18n/ar.po
odoo/addons/queue_job_subscribe/i18n/bg.po
odoo/addons/queue_job_subscribe/i18n/ca.po
odoo/addons/queue_job_subscribe/i18n/da.po
odoo/addons/queue_job_subscribe/i18n/de.po
odoo/addons/queue_job_subscribe/i18n/el_GR.po
odoo/addons/queue_job_subscribe/i18n/es.po
odoo/addons/queue_job_subscribe/i18n/es_ES.po
odoo/addons/queue_job_subscribe/i18n/fi.po
odoo/addons/queue_job_subscribe/i18n/fr.po
odoo/addons/queue_job_subscribe/i18n/fr_CH.po
odoo/addons/queue_job_subscribe/i18n/hr.po
odoo/addons/queue_job_subscribe/i18n/hr_HR.po
odoo/addons/queue_job_subscribe/i18n/hu.po
odoo/addons/queue_job_subscribe/i18n/it.po
odoo/addons/queue_job_subscribe/i18n/nl.po
odoo/addons/queue_job_subscribe/i18n/pt_BR.po
odoo/addons/queue_job_subscribe/i18n/sl.po
odoo/addons/queue_job_subscribe/i18n/tr.po
odoo/addons/queue_job_subscribe/i18n/tr_TR.po
odoo/addons/queue_job_subscribe/i18n/zh_CN.po
odoo/addons/queue_job_subscribe/models/__init__.py
odoo/addons/queue_job_subscribe/models/queue_job.py
odoo/addons/queue_job_subscribe/models/res_users.py
odoo/addons/queue_job_subscribe/tests/__init__.py
odoo/addons/queue_job_subscribe/tests/test_job_subscribe.py
odoo/addons/queue_job_subscribe/views/res_users_view.xml
odoo11_addon_queue_job_subscribe-11.0.1.0.0.dist-info/DESCRIPTION.rst
odoo11_addon_queue_job_subscribe-11.0.1.0.0.dist-info/METADATA
odoo11_addon_queue_job_subscribe-11.0.1.0.0.dist-info/RECORD
odoo11_addon_queue_job_subscribe-11.0.1.0.0.dist-info/WHEEL
odoo11_addon_queue_job_subscribe-11.0.1.0.0.dist-info/metadata.json
odoo11_addon_queue_job_subscribe-11.0.1.0.0.dist-info/top_level.txt
